xdisplayinfo/__version__.py
xdisplayinfo/scripts/xdisplayinfo
xdisplayinfo-2.0.1.data/scripts/xdisplayinfo
xdisplayinfo-2.0.1.dist-info/LICENSE
xdisplayinfo-2.0.1.dist-info/METADATA
xdisplayinfo-2.0.1.dist-info/WHEEL
xdisplayinfo-2.0.1.dist-info/top_level.txt
xdisplayinfo-2.0.1.dist-info/RECORD
