Metadata-Version: 2.1
Name: xdisplayinfo
Version: 2.0.1
Summary: Utility to get information of the current display in systems using X.
Home-page: https://github.com/lu0/current-x-display-info
Author: Lucero Alvarado Ruiz
Author-email: me@lucerocodes.com
Project-URL: Source, https://github.com/lu0/current-x-display-info
Project-URL: Documentation, https://github.com/lu0/current-x-display-info#x-display-info
Project-URL: Tracker, https://github.com/lu0/current-x-display-info/issues
Classifier: Development Status :: 3 - Alpha
Classifier: Environment :: Console
Classifier: Environment :: X11 Applications
Classifier: Intended Audience :: Developers
Classifier: License :: OSI Approved :: GNU General Public License v3 (GPLv3)
Classifier: Natural Language :: English
Classifier: Operating System :: Unix
Classifier: Operating System :: POSIX :: Linux
Classifier: Programming Language :: Unix Shell
Classifier: Programming Language :: Python :: 3
Classifier: Programming Language :: Python :: Implementation :: CPython
Classifier: Topic :: Multimedia :: Video :: Display
Classifier: Topic :: Desktop Environment :: Window Managers
Classifier: Topic :: System :: Hardware
Classifier: Topic :: System :: Shells
Classifier: Topic :: Terminals
Classifier: Topic :: Utilities
Requires-Python: >=3.7, <4
License-File: LICENSE
